{
  "name": "Ryobi 18V ONE+ 165mm Circular Saw - Skin Only",
  "slug": "ryobi-18v-one-circular-saw",
  "brand": "Ryobi",
  "category": "Power Saws",
  "subcategory": "Circular Saws",
  "bunningsSku": "6210595",
  "bunningsUrl": "https://www.bunnings.com.au/ryobi-18v-one-165mm-circular-saw-skin-only_p6210595",
  "thumbnailUrl": "src/images/tools/ryobi-18v-one-circular-saw.png",
  "specifications": {
    "power": "18V",
    "weight": "2.8 kg",
    "dimensions": "32 x 25 x 24 cm",
    "keyFeatures": [
      "165mm cutting capacity for various materials",
      "Compatible with 18V ONE+ battery system",
      "Lightweight and ergonomic design",
      "45° bevel cutting capability",
      "Laser guide for precise cutting"
    ],
    "batteryLife": "Up to 200 cuts per charge",
    "cordless": true
  },
  "pricing": {
    "currentPrice": 99,
    "currency": "AUD",
    "onSale": false
  },
  "popularity": {
    "reviewCount": 378,
    "averageRating": 4.4,
    "bunningsRank": 1
  }
}
